pyqtexa/__init__.py
pyqtexa/overlay/__init__.py
pyqtexa/overlay/dialogs.py
pyqtexa/overlay/overlay_feature.py
pyqtexa/overlay/overlay_mixin.py
pyqtexa/overlay/popup_widget.py
pyqtexa/utils/__init__.py
pyqtexa/utils/property.py
pyqtexa/utils/static.py
pyqtexa/utils/table_proxy.py
pyqtexa/widgets/__init__.py
pyqtexa/widgets/box_layout.py
pyqtexa/widgets/button.py
pyqtexa/widgets/divider.py
pyqtexa/widgets/image_views.py
pyqtexa/widgets/label.py
pyqtexa/widgets/line_edit.py
pyqtexa/widgets/options.py
pyqtexa/widgets/scroll.py
pyqtexa/widgets/table.py
pyqtexa/widgets/tabs.py
pyqtexa/widgets/widget.py
pyqtexa/widgets/window.py
pyqtexa-0.1.5.dist-info/METADATA
pyqtexa-0.1.5.dist-info/WHEEL
pyqtexa-0.1.5.dist-info/RECORD
