Metadata-Version: 2.4
Name: pyqtexa
Version: 0.1.5
Summary: Extensions for PyQt
Author: zapiy
Author-email: 4ikosa@gmail.com
Requires-Python: >=3.13
Classifier: Programming Language :: Python :: 3
Classifier: Programming Language :: Python :: 3.13
Classifier: Programming Language :: Python :: 3.14
Requires-Dist: pyqt6 (>=6.10.1,<7.0.0)
Project-URL: Homepage, https://github.com/oesand/pyqtexa
Project-URL: Repository, https://github.com/oesand/pyqtexa
